django_zappa_event_schedular/__init__.py
django_zappa_event_schedular/admin.py
django_zappa_event_schedular/apps.py
django_zappa_event_schedular/constants.py
django_zappa_event_schedular/models.py
django_zappa_event_schedular/tests.py
django_zappa_event_schedular/utils.py
django_zappa_event_schedular/validators.py
django_zappa_event_schedular/migrations/0001_initial.py
django_zappa_event_schedular/migrations/__init__.py
django_zappa_event_schedular-0.1.7b0.dist-info/METADATA
django_zappa_event_schedular-0.1.7b0.dist-info/WHEEL
django_zappa_event_schedular-0.1.7b0.dist-info/top_level.txt
django_zappa_event_schedular-0.1.7b0.dist-info/RECORD
