Metadata-Version: 2.1
Name: django-zappa-event-schedular
Version: 0.1.7b0
Summary: A Django app to schedule task.
Home-page: https://github.com/tushar1328/django-zappa-event-schedular
Author: Tushar Patel
Author-email: tushar@djangoboy.in
License: MIT
Project-URL: Source, https://github.com/tushar1328/django-zappa-event-schedular
Project-URL: Documentation, https://django-zappa-event-schedular.readthedocs.io/en/latest/#
Platform: UNKNOWN
Classifier: Environment :: Web Environment
Classifier: Framework :: Django
Classifier: Framework :: Django :: 3.2
Classifier: Intended Audience :: Developers
Classifier: License :: OSI Approved :: BSD License
Classifier: Operating System :: OS Independent
Classifier: Programming Language :: Python
Classifier: Programming Language :: Python :: 3
Classifier: Programming Language :: Python :: 3 :: Only
Classifier: Programming Language :: Python :: 3.8
Classifier: Programming Language :: Python :: 3.9
Classifier: Topic :: Internet :: WWW/HTTP
Classifier: Topic :: Internet :: WWW/HTTP :: Dynamic Content
Requires-Python: >=3.6
Requires-Dist: Django (>=3.2)
